{
	"BatchList": [
		{
			"BatchID": 1,
			"BatchName": "Batch 001",
			"AccountNumber": 46733,
			"DocCount": 20,
			"Datetime": "10/12/2023",
			"Status": "Processed"
		},
		{
			"BatchID": 2,
			"BatchName": "Batch 002",
			"AccountNumber": 46733,
			"DocCount": 20,
			"Datetime": "10/12/2023",
			"Status": "Processed"
		},
		{
			"BatchID": 3,
			"BatchName": "Batch 003",
			"AccountNumber": 46734,
			"DocCount": 22,
			"Datetime": "10/12/2023",
			"Status": "Pending"
		},
		{
			"BatchID": 4,
			"BatchName": "Batch 004",
			"AccountNumber": 67343,
			"DocCount": 20,
			"Datetime": "10/12/2023",
			"Status": "Processed"
		},
		{
			"BatchID": 5,
			"BatchName": "Batch 005",
			"AccountNumber": 67344,
			"DocCount": 20,
			"Datetime": "10/12/2023",
			"Status": "Processed"
		},
		{
			"BatchID": 6,
			"BatchName": "Batch 006",
			"AccountNumber": 78934,
			"DocCount": 22,
			"Datetime": "10/12/2023",
			"Status": "Pending"
		},
		{
			"BatchID": 7,
			"BatchName": "Batch 007",
			"AccountNumber": 78935,
			"DocCount": 20,
			"Datetime": "10/12/2023",
			"Status": "Processed"
		},
		{
			"BatchID": 8,
			"BatchName": "Batch 008",
			"AccountNumber": 78936,
			"DocCount": 20,
			"Datetime": "10/12/2023",
			"Status": "Processed"
		},
		{
			"BatchID": 9,
			"BatchName": "Batch 009",
			"AccountNumber": 78937,
			"DocCount": 22,
			"Datetime": "10/12/2023",
			"Status": "Pending"
		},
		{
			"BatchID": 10,
			"BatchName": "Batch 010",
			"AccountNumber": 78938,
			"DocCount": 20,
			"Datetime": "10/12/2023",
			"Status": "Processed"
		},
		{
			"BatchID": 11,
			"BatchName": "Batch 011",
			"AccountNumber": 78939,
			"DocCount": 20,
			"Datetime": "10/12/2023",
			"Status": "Processed"
		},
		{
			"BatchID": 12,
			"BatchName": "Batch 012",
			"AccountNumber": 78940,
			"DocCount": 22,
			"Datetime": "10/12/2023",
			"Status": "Pending"
		},
		{
			"BatchID": 13,
			"BatchName": "Batch 013",
			"AccountNumber": 78941,
			"DocCount": 20,
			"Datetime": "10/12/2023",
			"Status": "Processed"
		},
		{
			"BatchID": 14,
			"BatchName": "Batch 014",
			"AccountNumber": 78942,
			"DocCount": 20,
			"Datetime": "10/12/2023",
			"Status": "Processed"
		},
		{
			"BatchID": 15,
			"BatchName": "Batch 015",
			"AccountNumber": 78943,
			"DocCount": 22,
			"Datetime": "10/12/2023",
			"Status": "Pending"
		},
		{
			"BatchID": 16,
			"BatchName": "Batch 016",
			"AccountNumber": 78944,
			"DocCount": 20,
			"Datetime": "10/12/2023",
			"Status": "Processed"
		},
		{
			"BatchID": 17,
			"BatchName": "Batch 017",
			"AccountNumber": 78945,
			"DocCount": 20,
			"Datetime": "10/12/2023",
			"Status": "Processed"
		},
		{
			"BatchID": 18,
			"BatchName": "Batch 018",
			"AccountNumber": 78946,
			"DocCount": 22,
			"Datetime": "10/12/2023",
			"Status": "Pending"
		},
		{
			"BatchID": 19,
			"BatchName": "Batch 019",
			"AccountNumber": 78947,
			"DocCount": 21,
			"Datetime": "10/12/2023",
			"Status": "Processed"
		}
	],
	"UserList": [
		{
			"UserID": 1,
			"UserName": "Jsmith",
			"Email": "james.Smith@test.com",
			"FirstName": "James",
			"LastName": "Smith",
			"UserRole": "User",
			"Customer": "Customer 1",
			"AccountAccess": "67343,67344",
			"Lastlogiondate/time": "10/10/2023 15:23",
			"Language": "GB English",
			"ContactNo": "0044 7886373632",
    			"AccountAccess": [
      			{
        			"AccountNumber": "67343",
        			"AccountID": 1
      			},
      			{
        			"AccountNumber": "67344",
        			"AccountID": 2
      			}
    		]
		},
		{
			"UserID": 2,
			"UserName": "Jdoe",
			"Email": "Jane.Doe@test.com",
			"FirstName": "Jane",
			"LastName": "Doe",
			"UserRole": "User",
			"Customer": "Customer 2",
			"AccountAccess": 67343,
			"Lastlogiondate/time": "11/09/2022 13:34",
			"Language": "GB English",
			"ContactNo": "0044 7938432342",
			 "AccountAccess": [
			{
        			"AccountID": 1,
        			"AccountNumber": 67343
    			}
    		]
		},
		{
			"UserID": 3,
			"UserName": "NSmith",
			"Email": "nick.Smith@test123.com",
			"FirstName": "Nick",
			"LastName": "Smith",
			"UserRole": "User",
			"Customer": "Customer 3",
			"AccountAccess": "67343,67344",
			"Lastlogiondate/time": "09/09/2023 12:11",
			"Language": "GB English",
			"ContactNo": "0044 1743338432"
		},
		{
			"UserID": 4,
			"UserName": "CHughes",
			"Email": "Chris.Hughes@test123.com",
			"FirstName": "Chris",
			"LastName": "Hughes",
			"UserRole": "User",
			"Customer": "Customer 4",
			"AccountAccess": 67344,
			"Lastlogiondate/time": "07/10/2023 11:11",
			"Language": "GB English",
			"ContactNo": "0044 1628343234"
		},
		{
			"UserID": 5,
			"UserName": "DSmyth",
			"Email": "dave.smyth@test.com",
			"FirstName": "Dave ",
			"LastName": "Smyth",
			"UserRole": "User",
			"Customer": "Customer 5",
			"AccountAccess": 78934,
			"Lastlogiondate/time": "10/10/2023 15:23",
			"Language": "GB English",
			"ContactNo": "45 7886373632"
		},
		{
			"UserID": 6,
			"UserName": "AWells",
			"Email": "alice.wells@test.com",
			"FirstName": "Alice ",
			"LastName": "Wells",
			"UserRole": "User",
			"Customer": "Customer 6",
			"AccountAccess": 78935,
			"Lastlogiondate/time": "11/09/2022 13:34",
			"Language": "GB English",
			"ContactNo": "45 7938432342"
		},
		{
			"UserID": 7,
			"UserName": "BHarper",
			"Email": "bethany.harper@test123.com",
			"FirstName": "Bethany ",
			"LastName": "Harper",
			"UserRole": "User",
			"Customer": "Customer 7",
			"AccountAccess": 78936,
			"Lastlogiondate/time": "09/09/2023 13:20",
			"Language": "GB English",
			"ContactNo": "45 1743338432"
		},
		{
			"UserID": 8,
			"UserName": "SSmith",
			"Email": "sally.smith@test123.com",
			"FirstName": "Sally ",
			"LastName": "Smith",
			"UserRole": "User",
			"Customer": "Customer 8",
			"AccountAccess": 78937,
			"Lastlogiondate/time": "07/10/2023 11:11",
			"Language": "GB English",
			"ContactNo": "45 1628343234"
		},
		{
			"UserID": 9,
			"UserName": "SBeecham",
			"Email": "stuart.beecham@test.com",
			"FirstName": "Stuart ",
			"LastName": "Beecham",
			"UserRole": "User",
			"Customer": "Customer 9",
			"AccountAccess": 78938,
			"Lastlogiondate/time": "10/10/2023 15:23",
			"Language": "GB English",
			"ContactNo": "46 7886373632"
		},
		{
			"UserID": 10,
			"UserName": "ISingh",
			"Email": "indy.singh@test.com",
			"FirstName": "Indy ",
			"LastName": "Singh",
			"UserRole": "User",
			"Customer": "Customer 10",
			"AccountAccess": 78939,
			"Lastlogiondate/time": "11/09/2022 13:34",
			"Language": "GB English",
			"ContactNo": "46 7938432342"
		},
		{
			"UserID": 11,
			"UserName": "JParker",
			"Email": "jame.parker@test123.com",
			"FirstName": "James ",
			"LastName": "Parker",
			"UserRole": "User",
			"Customer": "Customer 11",
			"AccountAccess": 78940,
			"Lastlogiondate/time": "09/09/2023 12:15",
			"Language": "GB English",
			"ContactNo": "46 1743338432"
		},
		{
			"UserID": 12,
			"UserName": "OHughes",
			"Email": "oliver.hughes@test123.com",
			"FirstName": "Oliver ",
			"LastName": "Hughes",
			"UserRole": "User",
			"Customer": "Customer 12",
			"AccountAccess": 78941,
			"Lastlogiondate/time": "10/07/2023 11:47",
			"Language": "GB English",
			"ContactNo": "46 1628343234"
		},
		{
			"UserID": 13,
			"UserName": "LHarper",
			"Email": "lee.harper@test.com",
			"FirstName": "Len ",
			"LastName": "Harper",
			"UserRole": "User",
			"Customer": "Customer 13",
			"AccountAccess": 78942,
			"Lastlogiondate/time": "10/10/2023 15:23",
			"Language": "GB English",
			"ContactNo": "47 7886373632"
		},
		{
			"UserID": 14,
			"UserName": "JGower",
			"Email": "jane.gower@test.com",
			"FirstName": "Jane ",
			"LastName": "Gower",
			"UserRole": "User",
			"Customer": "Customer 14",
			"AccountAccess": 78943,
			"Lastlogiondate/time": "11/09/2022 13:34",
			"Language": "GB English",
			"ContactNo": "47 7938432342"
		},
		{
			"UserID": 15,
			"UserName": "AGunn",
			"Email": "alistair.gunn@test123.com",
			"FirstName": "Alistair ",
			"LastName": "Gunn",
			"UserRole": "User",
			"Customer": "Customer 15",
			"AccountAccess": 78944,
			"Lastlogiondate/time": "09/09/2023 12:29",
			"Language": "GB English",
			"ContactNo": "47 1743338432"
		},
		{
			"UserID": 16,
			"UserName": "PBailey",
			"Email": "patricia.bailey@test123.com",
			"FirstName": "Patricia ",
			"LastName": "Bailey",
			"UserRole": "User",
			"Customer": "Customer 16",
			"AccountAccess": 78945,
			"Lastlogiondate/time": "10/07/2023 11:14",
			"Language": "GB English",
			"ContactNo": "47 1628343234"
		}
	]
}
